option_and_result/__init__.py
option_and_result/py.typed
babichjacob_option_and_result-0.2.3.dist-info/WHEEL
babichjacob_option_and_result-0.2.3.dist-info/METADATA
babichjacob_option_and_result-0.2.3.dist-info/RECORD
