Metadata-Version: 2.1
Name: babichjacob-option-and-result
Version: 0.2.3
Summary: A Python implementation of Rust's Option and Result
Home-page: https://github.com/babichjacob/python-option-and-result
License: MIT
Author: J or Jacob Babich
Author-email: jacobbabichpublic+git@gmail.com
Requires-Python: >=3.0,<4.0
Classifier: License :: OSI Approved :: MIT License
Classifier: Programming Language :: Python :: 3
Classifier: Programming Language :: Python :: 3.4
Classifier: Programming Language :: Python :: 3.5
Classifier: Programming Language :: Python :: 3.6
Classifier: Programming Language :: Python :: 3.7
Classifier: Programming Language :: Python :: 3.8
Classifier: Programming Language :: Python :: 3.9
Classifier: Programming Language :: Python :: 3.10
Classifier: Programming Language :: Python :: 3.11
Project-URL: Repository, https://github.com/babichjacob/python-option-and-result
